{
  "_meta": {
    "source": "공시지원금.xlsx",
    "note": "모델명 기준 요금제별 공시지원금(숫자만 반영)"
  },
  "아이폰13 128G": {
    "5G 초이스 스페셜": 600000,
    "5G 초이스 베이직": 600000,
    "5G 심플 110GB": 492000,
    "5G 슬림 10GB": 450000,
    "LTE 베이직": 386000,
    "ON 톡 플러스": 433000
  },
  "iPhone 15 128G": {
    "5G 초이스 스페셜": 600000,
    "5G 초이스 베이직": 600000,
    "5G 심플 110GB": 445000,
    "5G 슬림 10GB": 330000,
    "LTE 베이직": 156000,
    "ON 톡 플러스": 283000
  },
  "iPhone 15 256G": {
    "5G 초이스 스페셜": 600000,
    "5G 초이스 베이직": 600000,
    "5G 심플 110GB": 445000,
    "5G 슬림 10GB": 330000,
    "LTE 베이직": 156000,
    "ON 톡 플러스": 283000
  },
  "iPhone 15 512G": {
    "5G 초이스 스페셜": 600000,
    "5G 초이스 베이직": 600000,
    "5G 심플 110GB": 445000,
    "5G 슬림 10GB": 330000,
    "LTE 베이직": 156000,
    "ON 톡 플러스": 283000
  },
  "iPhone 15 Plus 128G": {
    "5G 초이스 스페셜": 600000,
    "5G 초이스 베이직": 600000,
    "5G 심플 110GB": 445000,
    "5G 슬림 10GB": 330000,
    "LTE 베이직": 156000,
    "ON 톡 플러스": 283000
  },
  "iPhone 15 Plus 256G": {
    "5G 초이스 스페셜": 600000,
    "5G 초이스 베이직": 600000,
    "5G 심플 110GB": 445000,
    "5G 슬림 10GB": 330000,
    "LTE 베이직": 156000,
    "ON 톡 플러스": 283000
  },
  "iPhone 15 Plus 512G": {
    "5G 초이스 스페셜": 600000,
    "5G 초이스 베이직": 600000,
    "5G 심플 110GB": 445000,
    "5G 슬림 10GB": 330000,
    "LTE 베이직": 156000,
    "ON 톡 플러스": 283000
  },
  "iPhone 15 Pro 128G": {
    "5G 초이스 스페셜": 600000,
    "5G 초이스 베이직": 600000,
    "5G 심플 110GB": 445000,
    "5G 슬림 10GB": 330000,
    "LTE 베이직": 156000,
    "ON 톡 플러스": 283000
  },
  "iPhone 15 Pro 256G": {
    "5G 초이스 스페셜": 600000,
    "5G 초이스 베이직": 600000,
    "5G 심플 110GB": 445000,
    "5G 슬림 10GB": 330000,
    "LTE 베이직": 156000,
    "ON 톡 플러스": 283000
  },
  "iPhone 15 Pro 512G": {
    "5G 초이스 스페셜": 600000,
    "5G 초이스 베이직": 600000,
    "5G 심플 110GB": 445000,
    "5G 슬림 10GB": 330000,
    "LTE 베이직": 156000,
    "ON 톡 플러스": 283000
  },
  "iPhone 15 Pro 1T": {
    "5G 초이스 스페셜": 600000,
    "5G 초이스 베이직": 600000,
    "5G 심플 110GB": 445000,
    "5G 슬림 10GB": 330000,
    "LTE 베이직": 156000,
    "ON 톡 플러스": 283000
  },
  "iPhone 15 Pro Max 256G": {
    "5G 초이스 스페셜": 600000,
    "5G 초이스 베이직": 600000,
    "5G 심플 110GB": 445000,
    "5G 슬림 10GB": 330000,
    "LTE 베이직": 156000,
    "ON 톡 플러스": 283000
  },
  "iPhone 15 Pro Max 512G": {
    "5G 초이스 스페셜": 600000,
    "5G 초이스 베이직": 600000,
    "5G 심플 110GB": 445000,
    "5G 슬림 10GB": 330000,
    "LTE 베이직": 156000,
    "ON 톡 플러스": 283000
  },
  "iPhone 15 Pro Max 1T": {
    "5G 초이스 스페셜": 600000,
    "5G 초이스 베이직": 600000,
    "5G 심플 110GB": 445000,
    "5G 슬림 10GB": 330000,
    "LTE 베이직": 156000,
    "ON 톡 플러스": 283000
  },
  "iPhone 17 256GB": {
    "5G 초이스 스페셜": 450000,
    "5G 초이스 베이직": 450000,
    "5G 심플 110GB": 340000,
    "5G 슬림 10GB": 262000,
    "LTE 베이직": 141000,
    "ON 톡 플러스": 229000
  },
  "iPhone 17 512GB": {
    "5G 초이스 스페셜": 450000,
    "5G 초이스 베이직": 450000,
    "5G 심플 110GB": 340000,
    "5G 슬림 10GB": 262000,
    "LTE 베이직": 141000,
    "ON 톡 플러스": 229000
  },
  "iPhone Air 256GB": {
    "5G 초이스 스페셜": 450000,
    "5G 초이스 베이직": 450000,
    "5G 심플 110GB": 340000,
    "5G 슬림 10GB": 262000,
    "LTE 베이직": 141000,
    "ON 톡 플러스": 229000
  },
  "iPhone Air 512GB": {
    "5G 초이스 스페셜": 450000,
    "5G 초이스 베이직": 450000,
    "5G 심플 110GB": 340000,
    "5G 슬림 10GB": 262000,
    "LTE 베이직": 141000,
    "ON 톡 플러스": 229000
  },
  "iPhone Air 1TB": {
    "5G 초이스 스페셜": 450000,
    "5G 초이스 베이직": 450000,
    "5G 심플 110GB": 340000,
    "5G 슬림 10GB": 262000,
    "LTE 베이직": 141000,
    "ON 톡 플러스": 229000
  },
  "iPhone 17 Pro 256GB": {
    "5G 초이스 스페셜": 450000,
    "5G 초이스 베이직": 450000,
    "5G 심플 110GB": 340000,
    "5G 슬림 10GB": 262000,
    "LTE 베이직": 141000,
    "ON 톡 플러스": 229000
  },
  "iPhone 17 Pro 512GB": {
    "5G 초이스 스페셜": 450000,
    "5G 초이스 베이직": 450000,
    "5G 심플 110GB": 340000,
    "5G 슬림 10GB": 262000,
    "LTE 베이직": 141000,
    "ON 톡 플러스": 229000
  },
  "iPhone 17 Pro 1TB": {
    "5G 초이스 스페셜": 450000,
    "5G 초이스 베이직": 450000,
    "5G 심플 110GB": 340000,
    "5G 슬림 10GB": 262000,
    "LTE 베이직": 141000,
    "ON 톡 플러스": 229000
  },
  "iPhone 17 Pro Max 256GB": {
    "5G 초이스 스페셜": 201000,
    "5G 초이스 베이직": 150000,
    "5G 심플 110GB": 127000,
    "5G 슬림 10GB": 100000,
    "LTE 베이직": 60000,
    "ON 톡 플러스": 89000
  },
  "iPhone 17 Pro Max 512GB": {
    "5G 초이스 스페셜": 201000,
    "5G 초이스 베이직": 150000,
    "5G 심플 110GB": 127000,
    "5G 슬림 10GB": 100000,
    "LTE 베이직": 60000,
    "ON 톡 플러스": 89000
  },
  "iPhone 17 Pro Max 1TB": {
    "5G 초이스 스페셜": 201000,
    "5G 초이스 베이직": 150000,
    "5G 심플 110GB": 127000,
    "5G 슬림 10GB": 100000,
    "LTE 베이직": 60000,
    "ON 톡 플러스": 89000
  },
  "iPhone 17 Pro Max 2TB": {
    "5G 초이스 스페셜": 201000,
    "5G 초이스 베이직": 150000,
    "5G 심플 110GB": 127000,
    "5G 슬림 10GB": 100000,
    "LTE 베이직": 60000,
    "ON 톡 플러스": 89000
  },
  "iPhone 16 128G": {
    "5G 초이스 스페셜": 600000,
    "5G 초이스 베이직": 600000,
    "5G 심플 110GB": 600000,
    "5G 슬림 10GB": 330000,
    "LTE 베이직": 156000,
    "ON 톡 플러스": 283000
  },
  "iPhone 16 256G": {
    "5G 초이스 스페셜": 600000,
    "5G 초이스 베이직": 600000,
    "5G 심플 110GB": 600000,
    "5G 슬림 10GB": 330000,
    "LTE 베이직": 156000,
    "ON 톡 플러스": 283000
  },
  "iPhone 16 512G": {
    "5G 초이스 스페셜": 600000,
    "5G 초이스 베이직": 600000,
    "5G 심플 110GB": 600000,
    "5G 슬림 10GB": 330000,
    "LTE 베이직": 156000,
    "ON 톡 플러스": 283000
  },
  "iPhone 16 Plus 128G": {
    "5G 초이스 스페셜": 600000,
    "5G 초이스 베이직": 600000,
    "5G 심플 110GB": 600000,
    "5G 슬림 10GB": 330000,
    "LTE 베이직": 156000,
    "ON 톡 플러스": 283000
  },
  "iPhone 16 Plus 256G": {
    "5G 초이스 스페셜": 600000,
    "5G 초이스 베이직": 600000,
    "5G 심플 110GB": 600000,
    "5G 슬림 10GB": 330000,
    "LTE 베이직": 156000,
    "ON 톡 플러스": 283000
  },
  "iPhone 16 Plus 512G": {
    "5G 초이스 스페셜": 600000,
    "5G 초이스 베이직": 600000,
    "5G 심플 110GB": 600000,
    "5G 슬림 10GB": 330000,
    "LTE 베이직": 156000,
    "ON 톡 플러스": 283000
  },
  "iPhone 16 Pro 128G": {
    "5G 초이스 스페셜": 600000,
    "5G 초이스 베이직": 600000,
    "5G 심플 110GB": 600000,
    "5G 슬림 10GB": 330000,
    "LTE 베이직": 156000,
    "ON 톡 플러스": 283000
  },
  "iPhone 16 Pro 256G": {
    "5G 초이스 스페셜": 600000,
    "5G 초이스 베이직": 600000,
    "5G 심플 110GB": 600000,
    "5G 슬림 10GB": 330000,
    "LTE 베이직": 156000,
    "ON 톡 플러스": 283000
  },
  "iPhone 16 Pro 512G": {
    "5G 초이스 스페셜": 600000,
    "5G 초이스 베이직": 600000,
    "5G 심플 110GB": 600000,
    "5G 슬림 10GB": 330000,
    "LTE 베이직": 156000,
    "ON 톡 플러스": 283000
  },
  "iPhone 16 Pro 1T": {
    "5G 초이스 스페셜": 600000,
    "5G 초이스 베이직": 600000,
    "5G 심플 110GB": 600000,
    "5G 슬림 10GB": 330000,
    "LTE 베이직": 156000,
    "ON 톡 플러스": 283000
  },
  "iPhone 16 Pro Max 256G": {
    "5G 초이스 스페셜": 600000,
    "5G 초이스 베이직": 600000,
    "5G 심플 110GB": 600000,
    "5G 슬림 10GB": 330000,
    "LTE 베이직": 156000,
    "ON 톡 플러스": 283000
  },
  "iPhone 16 Pro Max 512G": {
    "5G 초이스 스페셜": 600000,
    "5G 초이스 베이직": 600000,
    "5G 심플 110GB": 600000,
    "5G 슬림 10GB": 330000,
    "LTE 베이직": 156000,
    "ON 톡 플러스": 283000
  },
  "iPhone 16 Pro Max 1T": {
    "5G 초이스 스페셜": 600000,
    "5G 초이스 베이직": 600000,
    "5G 심플 110GB": 600000,
    "5G 슬림 10GB": 330000,
    "LTE 베이직": 156000,
    "ON 톡 플러스": 283000
  },
  "iPhone 16e 128G": {
    "5G 초이스 스페셜": 550000,
    "5G 초이스 베이직": 500000,
    "5G 심플 110GB": 478000,
    "5G 슬림 10GB": 430000,
    "LTE 베이직": 358000,
    "ON 톡 플러스": 411000
  },
  "iPhone 16e 256G": {
    "5G 초이스 스페셜": 550000,
    "5G 초이스 베이직": 500000,
    "5G 심플 110GB": 478000,
    "5G 슬림 10GB": 430000,
    "LTE 베이직": 358000,
    "ON 톡 플러스": 411000
  },
  "iPhone 16e 512G": {
    "5G 초이스 스페셜": 550000,
    "5G 초이스 베이직": 500000,
    "5G 심플 110GB": 478000,
    "5G 슬림 10GB": 430000,
    "LTE 베이직": 358000,
    "ON 톡 플러스": 411000
  },
  "갤럭시 S25": {
    "5G 초이스 스페셜": 500000,
    "5G 초이스 베이직": 500000,
    "5G 심플 110GB": 377000,
    "5G 슬림 10GB": 300000,
    "LTE 베이직": 183000,
    "ON 톡 플러스": 269000
  },
  "갤럭시 S25_ONE": {
    "5G 초이스 스페셜": 500000,
    "5G 초이스 베이직": 500000,
    "5G 심플 110GB": 377000,
    "5G 슬림 10GB": 300000,
    "LTE 베이직": 183000,
    "ON 톡 플러스": 269000
  },
  "갤럭시 S25 512GB": {
    "5G 초이스 스페셜": 500000,
    "5G 초이스 베이직": 500000,
    "5G 심플 110GB": 377000,
    "5G 슬림 10GB": 300000,
    "LTE 베이직": 183000,
    "ON 톡 플러스": 269000
  },
  "갤럭시 S25+": {
    "5G 초이스 스페셜": 500000,
    "5G 초이스 베이직": 500000,
    "5G 심플 110GB": 377000,
    "5G 슬림 10GB": 300000,
    "LTE 베이직": 183000,
    "ON 톡 플러스": 269000
  },
  "갤럭시 S25+ 512GB": {
    "5G 초이스 스페셜": 500000,
    "5G 초이스 베이직": 500000,
    "5G 심플 110GB": 377000,
    "5G 슬림 10GB": 300000,
    "LTE 베이직": 183000,
    "ON 톡 플러스": 269000
  },
  "갤럭시 S25 Ultra": {
    "5G 초이스 스페셜": 500000,
    "5G 초이스 베이직": 500000,
    "5G 심플 110GB": 377000,
    "5G 슬림 10GB": 300000,
    "LTE 베이직": 183000,
    "ON 톡 플러스": 269000
  },
  "갤럭시 S25 Ultra 512GB": {
    "5G 초이스 스페셜": 500000,
    "5G 초이스 베이직": 500000,
    "5G 심플 110GB": 377000,
    "5G 슬림 10GB": 300000,
    "LTE 베이직": 183000,
    "ON 톡 플러스": 269000
  },
  "갤럭시 S25 엣지": {
    "5G 초이스 스페셜": 600000,
    "5G 초이스 베이직": 600000,
    "5G 심플 110GB": 445000,
    "5G 슬림 10GB": 330000,
    "LTE 베이직": 156000,
    "ON 톡 플러스": 283000
  },
  "갤럭시 S25 엣지 512GB": {
    "5G 초이스 스페셜": 600000,
    "5G 초이스 베이직": 600000,
    "5G 심플 110GB": 445000,
    "5G 슬림 10GB": 330000,
    "LTE 베이직": 156000,
    "ON 톡 플러스": 283000
  },
  "갤럭시 S25 Edge_ONE": {
    "5G 초이스 스페셜": 600000,
    "5G 초이스 베이직": 600000,
    "5G 심플 110GB": 445000,
    "5G 슬림 10GB": 330000,
    "LTE 베이직": 156000,
    "ON 톡 플러스": 283000
  },
  "갤럭시 S25 Edge 512GB_ONE": {
    "5G 초이스 스페셜": 600000,
    "5G 초이스 베이직": 600000,
    "5G 심플 110GB": 445000,
    "5G 슬림 10GB": 330000,
    "LTE 베이직": 156000,
    "ON 톡 플러스": 283000
  },
  "갤럭시 S24": {
    "5G 초이스 스페셜": 650000,
    "5G 초이스 베이직": 650000,
    "5G 심플 110GB": 476000,
    "5G 슬림 10GB": 380000,
    "LTE 베이직": 235000,
    "ON 톡 플러스": 341000
  },
  "갤럭시 S24 512GB": {
    "5G 초이스 스페셜": 650000,
    "5G 초이스 베이직": 650000,
    "5G 심플 110GB": 476000,
    "5G 슬림 10GB": 380000,
    "LTE 베이직": 235000,
    "ON 톡 플러스": 341000
  },
  "갤럭시 S24+": {
    "5G 초이스 스페셜": 650000,
    "5G 초이스 베이직": 650000,
    "5G 심플 110GB": 476000,
    "5G 슬림 10GB": 380000,
    "LTE 베이직": 235000,
    "ON 톡 플러스": 341000
  },
  "갤럭시 S24+ 512GB": {
    "5G 초이스 스페셜": 650000,
    "5G 초이스 베이직": 650000,
    "5G 심플 110GB": 476000,
    "5G 슬림 10GB": 380000,
    "LTE 베이직": 235000,
    "ON 톡 플러스": 341000
  },
  "갤럭시 S24 Ultra": {
    "5G 초이스 스페셜": 650000,
    "5G 초이스 베이직": 650000,
    "5G 심플 110GB": 476000,
    "5G 슬림 10GB": 380000,
    "LTE 베이직": 235000,
    "ON 톡 플러스": 341000
  },
  "갤럭시 S24 Ultra 512GB": {
    "5G 초이스 스페셜": 650000,
    "5G 초이스 베이직": 650000,
    "5G 심플 110GB": 476000,
    "5G 슬림 10GB": 380000,
    "LTE 베이직": 235000,
    "ON 톡 플러스": 341000
  },
  "갤럭시S23 (256GB)": {
    "5G 초이스 스페셜": 600000,
    "5G 초이스 베이직": 600000,
    "5G 심플 110GB": 600000,
    "5G 슬림 10GB": 400000,
    "LTE 베이직": 246000,
    "ON 톡 플러스": 358000
  },
  "갤럭시S23+ (256GB)": {
    "5G 초이스 스페셜": 600000,
    "5G 초이스 베이직": 600000,
    "5G 심플 110GB": 600000,
    "5G 슬림 10GB": 400000,
    "LTE 베이직": 246000,
    "ON 톡 플러스": 358000
  },
  "갤럭시S23 울트라 (256GB)": {
    "5G 초이스 스페셜": 600000,
    "5G 초이스 베이직": 600000,
    "5G 심플 110GB": 600000,
    "5G 슬림 10GB": 400000,
    "LTE 베이직": 246000,
    "ON 톡 플러스": 358000
  },
  "갤럭시S24 FE": {
    "5G 초이스 스페셜": 600000,
    "5G 초이스 베이직": 600000,
    "5G 심플 110GB": 517000,
    "5G 슬림 10GB": 488000,
    "LTE 베이직": 444000,
    "ON 톡 플러스": 476000
  },
  "갤럭시S25 FE": {
    "5G 초이스 스페셜": 500000,
    "5G 초이스 베이직": 500000,
    "5G 심플 110GB": 500000,
    "5G 슬림 10GB": 300000,
    "LTE 베이직": 183000,
    "ON 톡 플러스": 269000
  },
  "갤럭시 S25 FE_ONE": {
    "5G 초이스 스페셜": 500000,
    "5G 초이스 베이직": 500000,
    "5G 심플 110GB": 500000,
    "5G 슬림 10GB": 300000,
    "LTE 베이직": 183000,
    "ON 톡 플러스": 269000
  },
  "갤럭시 Z Flip7 FE": {
    "5G 초이스 스페셜": 600000,
    "5G 초이스 베이직": 600000,
    "5G 심플 110GB": 445000,
    "5G 슬림 10GB": 330000,
    "LTE 베이직": 156000,
    "ON 톡 플러스": 283000
  },
  "갤럭시 Z Flip7": {
    "5G 초이스 스페셜": 600000,
    "5G 초이스 베이직": 600000,
    "5G 심플 110GB": 445000,
    "5G 슬림 10GB": 330000,
    "LTE 베이직": 156000,
    "ON 톡 플러스": 283000
  },
  "갤럭시 Z Flip7_ONE": {
    "5G 초이스 스페셜": 600000,
    "5G 초이스 베이직": 600000,
    "5G 심플 110GB": 445000,
    "5G 슬림 10GB": 330000,
    "LTE 베이직": 156000,
    "ON 톡 플러스": 283000
  },
  "갤럭시 Z Flip7 512GB": {
    "5G 초이스 스페셜": 600000,
    "5G 초이스 베이직": 600000,
    "5G 심플 110GB": 445000,
    "5G 슬림 10GB": 330000,
    "LTE 베이직": 156000,
    "ON 톡 플러스": 283000
  },
  "갤럭시 Z Fold7": {
    "5G 초이스 스페셜": 500000,
    "5G 초이스 베이직": 500000,
    "5G 심플 110GB": 377000,
    "5G 슬림 10GB": 300000,
    "LTE 베이직": 183000,
    "ON 톡 플러스": 269000
  },
  "갤럭시 Z Fold7 512GB": {
    "5G 초이스 스페셜": 500000,
    "5G 초이스 베이직": 500000,
    "5G 심플 110GB": 377000,
    "5G 슬림 10GB": 300000,
    "LTE 베이직": 183000,
    "ON 톡 플러스": 269000
  },
  "갤럭시 Z Flip6": {
    "5G 초이스 스페셜": 700000,
    "5G 초이스 베이직": 700000,
    "5G 심플 110GB": 650000,
    "5G 슬림 10GB": 450000,
    "LTE 베이직": 348000,
    "ON 톡 플러스": 422000
  },
  "갤럭시 Z Flip6 512GB": {
    "5G 초이스 스페셜": 700000,
    "5G 초이스 베이직": 700000,
    "5G 심플 110GB": 650000,
    "5G 슬림 10GB": 450000,
    "LTE 베이직": 348000,
    "ON 톡 플러스": 422000
  },
  "갤럭시 Z Fold6": {
    "5G 초이스 스페셜": 700000,
    "5G 초이스 베이직": 700000,
    "5G 심플 110GB": 650000,
    "5G 슬림 10GB": 450000,
    "LTE 베이직": 348000,
    "ON 톡 플러스": 422000
  },
  "갤럭시 Z Fold6 512GB": {
    "5G 초이스 스페셜": 700000,
    "5G 초이스 베이직": 700000,
    "5G 심플 110GB": 650000,
    "5G 슬림 10GB": 450000,
    "LTE 베이직": 348000,
    "ON 톡 플러스": 422000
  },
  "갤럭시 Z Flip6 마루는강쥐 에디션": {
    "5G 초이스 스페셜": 700000,
    "5G 초이스 베이직": 700000,
    "5G 심플 110GB": 650000,
    "5G 슬림 10GB": 450000,
    "LTE 베이직": 348000,
    "ON 톡 플러스": 422000
  },
  "갤럭시 Z Flip5": {
    "5G 초이스 스페셜": 750000,
    "5G 초이스 베이직": 750000,
    "5G 심플 110GB": 576000,
    "5G 슬림 10GB": 480000,
    "LTE 베이직": 235000,
    "ON 톡 플러스": 341000
  },
  "갤럭시 Z Fold5": {
    "5G 초이스 스페셜": 850000,
    "5G 초이스 베이직": 850000,
    "5G 심플 110GB": 595000,
    "5G 슬림 10GB": 480000,
    "LTE 베이직": 156000,
    "ON 톡 플러스": 283000
  },
  "갤럭시 Z Flip5 512GB": {
    "5G 초이스 스페셜": 750000,
    "5G 초이스 베이직": 750000,
    "5G 심플 110GB": 576000,
    "5G 슬림 10GB": 480000,
    "LTE 베이직": 235000,
    "ON 톡 플러스": 341000
  },
  "갤럭시 Z Fold5 512GB": {
    "5G 초이스 스페셜": 850000,
    "5G 초이스 베이직": 850000,
    "5G 심플 110GB": 595000,
    "5G 슬림 10GB": 480000,
    "LTE 베이직": 156000,
    "ON 톡 플러스": 283000
  },
  "갤럭시A36 5G": {
    "5G 초이스 스페셜": 435000,
    "5G 초이스 베이직": 435000,
    "5G 심플 110GB": 435000,
    "5G 슬림 10GB": 435000,
    "LTE 베이직": 435000,
    "ON 톡 플러스": 435000
  },
  "맘편안폰S": {
    "5G 초이스 스페셜": 435000,
    "5G 초이스 베이직": 435000,
    "5G 심플 110GB": 435000,
    "5G 슬림 10GB": 435000,
    "LTE 베이직": 435000,
    "ON 톡 플러스": 435000
  },
  "갤럭시 Jump4": {
    "5G 초이스 스페셜": 392000,
    "5G 초이스 베이직": 392000,
    "5G 심플 110GB": 392000,
    "5G 슬림 10GB": 392000,
    "LTE 베이직": 392000,
    "ON 톡 플러스": 392000
  },
  "갤럭시 Jump3": {
    "5G 초이스 스페셜": 430000,
    "5G 초이스 베이직": 430000,
    "5G 심플 110GB": 430000,
    "5G 슬림 10GB": 430000,
    "LTE 베이직": 430000,
    "ON 톡 플러스": 430000
  },
  "엣지50퓨전": {
    "5G 초이스 스페셜": 330000,
    "5G 초이스 베이직": 330000,
    "5G 심플 110GB": 330000,
    "5G 슬림 10GB": 330000,
    "LTE 베이직": 330000,
    "ON 톡 플러스": 330000
  },
  "moto G56 5G": {
    "5G 초이스 스페셜": 290000,
    "5G 초이스 베이직": 290000,
    "5G 심플 110GB": 290000,
    "5G 슬림 10GB": 290000,
    "LTE 베이직": 290000,
    "ON 톡 플러스": 290000
  },
  "G34 5G": {
    "5G 초이스 스페셜": 184000,
    "5G 초이스 베이직": 184000,
    "5G 심플 110GB": 184000,
    "5G 슬림 10GB": 184000,
    "LTE 베이직": 184000,
    "ON 톡 플러스": 184000
  },
  "샤오미 14T": {
    "5G 초이스 스페셜": 522000,
    "5G 초이스 베이직": 522000,
    "5G 심플 110GB": 481000,
    "5G 슬림 10GB": 391000,
    "LTE 베이직": 255000,
    "ON 톡 플러스": 355000
  },
  "레드미노트 14 5G": {
    "5G 초이스 스페셜": 278000,
    "5G 초이스 베이직": 278000,
    "5G 심플 110GB": 278000,
    "5G 슬림 10GB": 278000,
    "LTE 베이직": 278000,
    "ON 톡 플러스": 278000
  },
  "레드미 노트 14 프로 5G": {
    "5G 초이스 스페셜": 348000,
    "5G 초이스 베이직": 348000,
    "5G 심플 110GB": 348000,
    "5G 슬림 10GB": 348000,
    "LTE 베이직": 348000,
    "ON 톡 플러스": 348000
  },
  "레드미 노트 14 프로 5G 512": {
    "5G 초이스 스페셜": 435000,
    "5G 초이스 베이직": 435000,
    "5G 심플 110GB": 435000,
    "5G 슬림 10GB": 435000,
    "LTE 베이직": 435000,
    "ON 톡 플러스": 435000
  },
  "갤럭시 A24": {
    "5G 초이스 스페셜": 345000,
    "5G 초이스 베이직": 345000,
    "5G 심플 110GB": 345000,
    "5G 슬림 10GB": 345000,
    "LTE 베이직": 345000,
    "ON 톡 플러스": 345000
  },
  "갤럭시 A15": {
    "5G 초이스 스페셜": 300000,
    "5G 초이스 베이직": 300000,
    "5G 심플 110GB": 297000,
    "5G 슬림 10GB": 289000,
    "LTE 베이직": 277000,
    "ON 톡 플러스": 286000
  },
  "갤럭시 A16": {
    "5G 초이스 스페셜": 278000,
    "5G 초이스 베이직": 278000,
    "5G 심플 110GB": 278000,
    "5G 슬림 10GB": 278000,
    "LTE 베이직": 278000,
    "ON 톡 플러스": 278000
  },
  "갤럭시 A17": {
    "5G 초이스 스페셜": 278000,
    "5G 초이스 베이직": 278000,
    "5G 심플 110GB": 278000,
    "5G 슬림 10GB": 278000,
    "LTE 베이직": 278000,
    "ON 톡 플러스": 278000
  },
  "갤럭시 A17_ONE": {
    "5G 초이스 스페셜": 278000,
    "5G 초이스 베이직": 278000,
    "5G 심플 110GB": 278000,
    "5G 슬림 10GB": 278000,
    "LTE 베이직": 278000,
    "ON 톡 플러스": 278000
  },
  "시나모롤 키즈폰": {
    "5G 초이스 스페셜": 239000,
    "5G 초이스 베이직": 239000,
    "5G 심플 110GB": 239000,
    "5G 슬림 10GB": 239000,
    "LTE 베이직": 239000,
    "ON 톡 플러스": 239000
  },
  "폼폼푸린 키즈폰": {
    "5G 초이스 스페셜": 305000,
    "5G 초이스 베이직": 305000,
    "5G 심플 110GB": 305000,
    "5G 슬림 10GB": 305000,
    "LTE 베이직": 305000,
    "ON 톡 플러스": 305000
  },
  "레드미 노트 12": {
    "5G 초이스 스페셜": 249000,
    "5G 초이스 베이직": 249000,
    "5G 심플 110GB": 249000,
    "5G 슬림 10GB": 249000,
    "LTE 베이직": 249000,
    "ON 톡 플러스": 249000
  },
  "레드미 14C": {
    "5G 초이스 스페셜": 190000,
    "5G 초이스 베이직": 190000,
    "5G 심플 110GB": 190000,
    "5G 슬림 10GB": 190000,
    "LTE 베이직": 190000,
    "ON 톡 플러스": 190000
  },
  "클래식 폴더": {
    "5G 초이스 스페셜": 179000,
    "5G 초이스 베이직": 179000,
    "5G 심플 110GB": 179000,
    "5G 슬림 10GB": 179000,
    "LTE 베이직": 179000,
    "ON 톡 플러스": 179000
  },
  "펫네임": {
    "5G 초이스 스페셜": 15
  },
  "Apple Watch Series 10 42mm 알루미늄": {
    "5G 초이스 스페셜": 50000
  },
  "Apple Watch Series 10 42mm 티타늄": {
    "5G 초이스 스페셜": 50000
  },
  "Apple Watch Series 10 46mm 알루미늄": {
    "5G 초이스 스페셜": 50000
  },
  "Apple Watch Series 10 46mm 티타늄": {
    "5G 초이스 스페셜": 50000
  },
  "Apple Watch Ultra2 49mm 내추럴 티타늄": {
    "5G 초이스 스페셜": 50000
  },
  "Apple Watch Series 11 42mm 알루미늄": {
    "5G 초이스 스페셜": 50000
  },
  "Apple Watch Series 11 42mm 티타늄": {
    "5G 초이스 스페셜": 50000
  },
  "Apple Watch Series 11 46mm 알루미늄": {
    "5G 초이스 스페셜": 50000
  },
  "Apple Watch Series 11 46mm 티타늄": {
    "5G 초이스 스페셜": 50000
  },
  "Apple Watch SE3 40mm 알루미늄": {
    "5G 초이스 스페셜": 50000
  },
  "Apple Watch SE3 44mm 알루미늄": {
    "5G 초이스 스페셜": 50000
  },
  "Apple Watch Ultra 3 49mm 티타늄": {
    "5G 초이스 스페셜": 50000
  },
  "갤럭시 워치8 40mm": {
    "5G 초이스 스페셜": 150000
  },
  "갤럭시 워치8 44mm": {
    "5G 초이스 스페셜": 150000
  },
  "갤럭시 워치8 클래식 46mm": {
    "5G 초이스 스페셜": 150000
  },
  "갤럭시 워치 울트라 2025": {
    "5G 초이스 스페셜": 470000
  },
  "갤럭시 워치7 40mm": {
    "5G 초이스 스페셜": 130000
  },
  "갤럭시 워치7 44mm": {
    "5G 초이스 스페셜": 170000
  },
  "갤럭시 워치 울트라": {
    "5G 초이스 스페셜": 500000
  },
  "갤럭시 워치6 40mm": {
    "5G 초이스 스페셜": 180000
  },
  "갤럭시 워치6 44mm": {
    "5G 초이스 스페셜": 180000
  },
  "갤럭시 워치6 클래식 43mm": {
    "5G 초이스 스페셜": 200000
  },
  "갤럭시 워치6 클래식 47mm": {
    "5G 초이스 스페셜": 200000
  },
  "서피스 프로9 5G": {
    "5G 초이스 스페셜": 100000
  },
  "갤럭시북 GO 5G": {
    "5G 초이스 스페셜": 200000
  },
  "Tab S10 FE": {
    "5G 초이스 스페셜": 200000
  },
  "Tab S10 FE+": {
    "5G 초이스 스페셜": 200000
  },
  "Galaxy Tab S9": {
    "5G 초이스 스페셜": 200000
  },
  "Galaxy Tab S9 Plus": {
    "5G 초이스 스페셜": 200000
  },
  "갤럭시 탭 S10+ 5G": {
    "5G 초이스 스페셜": 150000
  },
  "갤럭시 탭 S10 Ultra 5G": {
    "5G 초이스 스페셜": 150000
  },
  "갤럭시 탭 A9+": {
    "5G 초이스 스페셜": 200000
  },
  "갤럭시탭 S11 Ultra 256G": {
    "5G 초이스 스페셜": 150000
  },
  "갤럭시탭 S11 Ultra 512G": {
    "5G 초이스 스페셜": 150000
  },
  "갤럭시탭 S11 128G": {
    "5G 초이스 스페셜": 150000
  },
  "갤럭시탭 S11 256G": {
    "5G 초이스 스페셜": 150000
  },
  "갤럭시탭 A11 Plus": {
    "5G 초이스 스페셜": 200000
  },
  "갤럭시북3 Go 5G": {
    "5G 초이스 스페셜": 300000
  },
  "iPad 11세대 A16 128G": {
    "5G 초이스 스페셜": 100000
  },
  "iPad 11세대 A16 256G": {
    "5G 초이스 스페셜": 100000
  },
  "iPad 11세대 A16 512G": {
    "5G 초이스 스페셜": 100000
  },
  "iPad Air M3 13\" 128G": {
    "5G 초이스 스페셜": 100000
  },
  "iPad Air M3 13\" 256G": {
    "5G 초이스 스페셜": 100000
  },
  "iPad Air M3 13\" 512G": {
    "5G 초이스 스페셜": 100000
  },
  "iPad Air M3 13\" 1T": {
    "5G 초이스 스페셜": 100000
  },
  "iPad Air M3 11\" 128G": {
    "5G 초이스 스페셜": 100000
  },
  "iPad Air M3 11\" 256G": {
    "5G 초이스 스페셜": 100000
  },
  "iPad Air M3 11\" 512G": {
    "5G 초이스 스페셜": 100000
  },
  "iPad Air M3 11\" 1T": {
    "5G 초이스 스페셜": 100000
  },
  "iPad Pro 11\" M4 256GB-NEW": {
    "5G 초이스 스페셜": 100000
  },
  "iPad Pro 11\" M4 512GB-NEW": {
    "5G 초이스 스페셜": 100000
  },
  "iPad Pro 11\" M4 1TB-NEW": {
    "5G 초이스 스페셜": 100000
  },
  "iPad Pro 11\" M4 2TB-NEW": {
    "5G 초이스 스페셜": 100000
  },
  "iPad Pro 13\" M4 256GB-NEW": {
    "5G 초이스 스페셜": 100000
  },
  "iPad Pro 13\" M4 512GB-NEW": {
    "5G 초이스 스페셜": 100000
  },
  "iPad Pro 13\" M4 1TB-NEW": {
    "5G 초이스 스페셜": 100000
  },
  "iPad Pro 13\" M4 2TB-NEW": {
    "5G 초이스 스페셜": 100000
  },
  "iPad Pro 11\" M4 1TB Nano TextureGlass-NEW": {
    "5G 초이스 스페셜": 100000
  },
  "iPad Pro 11\" M4 2TB Nano TextureGlass-NEW": {
    "5G 초이스 스페셜": 100000
  },
  "iPad Pro 13\" M4 1TB Nano TextureGlass-NEW": {
    "5G 초이스 스페셜": 100000
  },
  "iPad Pro 13\" M4 2TB Nano TextureGlass-NEW": {
    "5G 초이스 스페셜": 100000
  },
  "iPad Pro 11\" M5 256GB": {
    "5G 초이스 스페셜": 100000
  },
  "iPad Pro 11\" M5 512GB": {
    "5G 초이스 스페셜": 100000
  },
  "iPad Pro 11\" M5 1TB": {
    "5G 초이스 스페셜": 100000
  },
  "iPad Pro 11\" M5 2TB": {
    "5G 초이스 스페셜": 100000
  },
  "iPad Pro 11\" M5 1TB NanoTextureGlass": {
    "5G 초이스 스페셜": 100000
  },
  "iPad Pro 11\" M5 2TB NanoTextureGlass": {
    "5G 초이스 스페셜": 100000
  },
  "iPad Pro 13\" M5 256GB": {
    "5G 초이스 스페셜": 100000
  },
  "iPad Pro 13\" M5 512GB": {
    "5G 초이스 스페셜": 100000
  },
  "iPad Pro 13\" M5 1TB": {
    "5G 초이스 스페셜": 100000
  },
  "iPad Pro 13\" M5 2TB": {
    "5G 초이스 스페셜": 100000
  },
  "iPad Pro 13\" M5 1TB NanoTextureGlass": {
    "5G 초이스 스페셜": 100000
  },
  "iPad Pro 13\" M5 2TB NanoTextureGlass": {
    "5G 초이스 스페셜": 100000
  },
  "iPad mini A17Pro 128GB-NEW": {
    "5G 초이스 스페셜": 100000
  },
  "iPad mini A17Pro 256GB-NEW": {
    "5G 초이스 스페셜": 100000
  },
  "iPad mini A17Pro 512GB-NEW": {
    "5G 초이스 스페셜": 100000
  },
  "iPad mini A17Pro 128GB": {
    "5G 초이스 스페셜": 100000
  },
  "iPad mini A17Pro 256GB": {
    "5G 초이스 스페셜": 100000
  },
  "iPad mini A17Pro 512GB": {
    "5G 초이스 스페셜": 100000
  },
  "iPad Air 11\" M2 128GB": {
    "5G 초이스 스페셜": 100000
  },
  "iPad Air 11\" M2 256GB": {
    "5G 초이스 스페셜": 100000
  },
  "iPad Air 11\" M2 512GB": {
    "5G 초이스 스페셜": 100000
  },
  "iPad Air 11\" M2 1T": {
    "5G 초이스 스페셜": 100000
  },
  "iPad Air 13\" M2 128GB": {
    "5G 초이스 스페셜": 100000
  },
  "iPad Air 13\" M2 256GB": {
    "5G 초이스 스페셜": 100000
  },
  "iPad Air 13\" M2 512GB": {
    "5G 초이스 스페셜": 100000
  },
  "iPad Air 13\" M2 1T": {
    "5G 초이스 스페셜": 100000
  },
  "iPad Pro 11\" M4 256GB": {
    "5G 초이스 스페셜": 100000
  },
  "iPad Pro 11\" M4 512GB": {
    "5G 초이스 스페셜": 100000
  },
  "iPad Pro 11\" M4 1TB": {
    "5G 초이스 스페셜": 100000
  },
  "iPad Pro 11\" M4 2TB": {
    "5G 초이스 스페셜": 100000
  },
  "iPad Pro 13\" M4 256GB": {
    "5G 초이스 스페셜": 100000
  },
  "iPad Pro 13\" M4 512GB": {
    "5G 초이스 스페셜": 100000
  },
  "iPad Pro 13\" M4 1TB": {
    "5G 초이스 스페셜": 100000
  },
  "iPad Pro 13\" M4 2TB": {
    "5G 초이스 스페셜": 100000
  },
  "iPad Pro 11\" M4 1TB Nano TextureGlass": {
    "5G 초이스 스페셜": 100000
  },
  "iPad Pro 11\" M4 2TB Nano TextureGlass": {
    "5G 초이스 스페셜": 100000
  },
  "iPad Pro 13\" M4 1TB Nano TextureGlass": {
    "5G 초이스 스페셜": 100000
  },
  "iPad Pro 13\" M4 2TB Nano TextureGlass": {
    "5G 초이스 스페셜": 100000
  },
  "갤럭시 북": {
    "5G 초이스 스페셜": 380000,
    "5G 초이스 베이직": 380000
  },
  "olleh tv tab": {
    "5G 초이스 스페셜": 110000,
    "5G 초이스 베이직": 110000
  },
  "지니TV탭 2": {
    "5G 초이스 스페셜": 147000,
    "5G 초이스 베이직": 147000
  },
  "GiGA Genie LTE2": {
    "5G 초이스 스페셜": 230000
  },
  "Egg Talk": {
    "5G 초이스 스페셜": 79000
  },
  "Slim egg 3": {
    "5G 초이스 스페셜": 100000
  },
  "USB egg": {
    "5G 초이스 스페셜": 86000
  },
  "5G EGG 2": {
    "5G 초이스 스페셜": 120000
  },
  "5G EGG 3": {
    "5G 초이스 스페셜": 120000
  }
}